daebus/__init__.py
daebus/modules/blueprint.py
daebus/modules/caller.py
daebus/modules/context.py
daebus/modules/daemon.py
daebus/modules/http.py
daebus/modules/logger.py
daebus/modules/pubsub.py
daebus/modules/redis_client.py
daebus/modules/websocket.py
daebus-0.0.31.dist-info/METADATA
daebus-0.0.31.dist-info/WHEEL
daebus-0.0.31.dist-info/licenses/LICENSE
daebus-0.0.31.dist-info/RECORD
