Metadata-Version: 2.4
Name: daebus
Version: 0.0.31
Summary: A lightweight framework for building Python background services with a Flask-like API, enabling seamless inter-service communication via Redis pub/sub.
Project-URL: Homepage, https://github.com/twestos/daebus
Project-URL: Issues, https://github.com/twestos/daebus/issues
Author-email: Tom West <tom@bambo.co>
License-Expression: MIT
License-File: LICENSE
Classifier: Intended Audience :: Developers
Classifier: Operating System :: OS Independent
Classifier: Programming Language :: Python :: 3
Requires-Python: >=3.9
Requires-Dist: apscheduler>=3.11.0
Requires-Dist: redis>=6.0.0
Requires-Dist: websockets>=15.0.1
Provides-Extra: dev
Requires-Dist: bump2version>=1.0.1; extra == 'dev'
Requires-Dist: codecov>=2.1.13; extra == 'dev'
Requires-Dist: flake8>=7.2.0; extra == 'dev'
Requires-Dist: pytest-asyncio>=0.26.0; extra == 'dev'
Requires-Dist: pytest-cov>=6.1.1; extra == 'dev'
Requires-Dist: pytest-mock>=3.14.0; extra == 'dev'
Requires-Dist: pytest>=8.3.5; extra == 'dev'
